bin/scheduler.py
builtin/__init__.py
builtin/avl_tree.py
builtin/collections.py
builtin/index.py
builtin/path.py
builtin/red_black_tree.py
builtin/time_dim.py
builtin/timeline.py
builtin/visual.py
core/__init__.py
core/base_symb.py
core/batch_processing.py
core/graph_traversal.py
core/lazy.py
core/lazy_symb.py
core/maturing.py
core/mixin_validator.py
core/mixinability.py
core/mixins.py
core/protocols.py
core/relations.py
core/schedule.py
core/symb.py
core/symbable.py
core/symbol.py
core/symbol_namespace.py
core/time_arithmetics.py
core/type_var_t.py
symb-0.0.10.dist-info/licenses/LICENSE
utils/memory.py
symb-0.0.10.dist-info/METADATA
symb-0.0.10.dist-info/WHEEL
symb-0.0.10.dist-info/entry_points.txt
symb-0.0.10.dist-info/top_level.txt
symb-0.0.10.dist-info/RECORD
