Metadata-Version: 2.4
Name: symb
Version: 0.0.10
Summary: A Lazy, Graph-Oriented, Immutable Symbol System Concept for Domain-Specific Abstraction
Author-email: Miklos Beky <miklos.beky@gmail.com>
Project-URL: homepage, https://github.com/ikko/symb
Project-URL: repository, https://github.com/ikko/symb
Project-URL: documentation, https://github.com/ikko/symb
Classifier: Development Status :: 2 - Pre-Alpha
Classifier: Programming Language :: Python :: 3
Classifier: License :: OSI Approved :: MIT License
Classifier: Operating System :: OS Independent
Requires-Python: >=3.10
License-File: LICENSE
Requires-Dist: orjson>=3.10.0
Requires-Dist: anyio>=4.4.0
Requires-Dist: libcst>=1.2.0
Requires-Dist: ipython>=8.18.1
Requires-Dist: typer>=0.12.3
Requires-Dist: croniter>=2.0.1
Requires-Dist: sniffio
Requires-Dist: PyYAML
Requires-Dist: pytz
Requires-Dist: python-dateutil
Requires-Dist: toml
Provides-Extra: dev
Requires-Dist: pytest; extra == "dev"
Requires-Dist: pytest-cov; extra == "dev"
Requires-Dist: pytest-anyio; extra == "dev"
Requires-Dist: mypy; extra == "dev"
Requires-Dist: pre-commit; extra == "dev"
Requires-Dist: sniffio; extra == "dev"
Requires-Dist: typer; extra == "dev"
Provides-Extra: visual
Requires-Dist: graphviz>=0.20.0; extra == "visual"
Provides-Extra: full
Requires-Dist: symb[visual]; extra == "full"
Dynamic: license-file
